django_graphql_social_auth-0.1.4.dist-info/DESCRIPTION.rst
django_graphql_social_auth-0.1.4.dist-info/METADATA
django_graphql_social_auth-0.1.4.dist-info/RECORD
django_graphql_social_auth-0.1.4.dist-info/WHEEL
django_graphql_social_auth-0.1.4.dist-info/metadata.json
django_graphql_social_auth-0.1.4.dist-info/top_level.txt
graphql_social_auth/__init__.py
graphql_social_auth/decorators.py
graphql_social_auth/exceptions.py
graphql_social_auth/mixins.py
graphql_social_auth/mutations.py
graphql_social_auth/types.py
graphql_social_auth/utils.py
graphql_social_auth/locale/es/LC_MESSAGES/django.mo
graphql_social_auth/locale/es/LC_MESSAGES/django.po
graphql_social_auth/relay/__init__.py
graphql_social_auth/relay/mutations.py
graphql_social_auth/relay/nodes.py
