Metadata-Version: 2.0
Name: django-graphql-social-auth
Version: 0.1.4
Summary: Python Social Auth support for Django GraphQL
Home-page: https://github.com/flavors/django-graphql-social-auth/
Author: mongkok
Author-email: domake.io@gmail.com
License: MIT
Platform: UNKNOWN
Classifier: Development Status :: 1 - Planning
Classifier: Environment :: Web Environment
Classifier: Intended Audience :: Developers
Classifier: License :: OSI Approved :: MIT License
Classifier: Operating System :: OS Independent
Classifier: Programming Language :: Python
Classifier: Programming Language :: Python :: 3
Classifier: Programming Language :: Python :: 3.4
Classifier: Programming Language :: Python :: 3.5
Classifier: Programming Language :: Python :: 3.6
Classifier: Programming Language :: Python :: 3.7
Classifier: Framework :: Django
Classifier: Framework :: Django :: 1.11
Classifier: Framework :: Django :: 2.0
Classifier: Framework :: Django :: 2.1
Classifier: Framework :: Django :: 2.2
Requires-Dist: Django (>=1.11)
Requires-Dist: django-filter (>=1.1.0)
Requires-Dist: graphene-django (>=2.0.0)
Requires-Dist: social-auth-app-django (>=2.1.0)
Provides-Extra: jwt
Requires-Dist: django-graphql-jwt (>=0.1.2); extra == 'jwt'
